EnglishAssistantCore/Core.py
EnglishAssistantCore/__init__.py
EnglishAssistantCore/nltk_data/corpora/brown/CONTENTS
EnglishAssistantCore/nltk_data/corpora/brown/README
EnglishAssistantCore/nltk_data/corpora/brown/ca01
EnglishAssistantCore/nltk_data/corpora/brown/ca02
EnglishAssistantCore/nltk_data/corpora/brown/ca03
EnglishAssistantCore/nltk_data/corpora/brown/ca04
EnglishAssistantCore/nltk_data/corpora/brown/ca05
EnglishAssistantCore/nltk_data/corpora/brown/ca06
EnglishAssistantCore/nltk_data/corpora/brown/ca07
EnglishAssistantCore/nltk_data/corpora/brown/ca08
EnglishAssistantCore/nltk_data/corpora/brown/ca09
EnglishAssistantCore/nltk_data/corpora/brown/ca10
EnglishAssistantCore/nltk_data/corpora/brown/ca11
EnglishAssistantCore/nltk_data/corpora/brown/ca12
EnglishAssistantCore/nltk_data/corpora/brown/ca13
EnglishAssistantCore/nltk_data/corpora/brown/ca14
EnglishAssistantCore/nltk_data/corpora/brown/ca15
EnglishAssistantCore/nltk_data/corpora/brown/ca16
EnglishAssistantCore/nltk_data/corpora/brown/ca17
EnglishAssistantCore/nltk_data/corpora/brown/ca18
EnglishAssistantCore/nltk_data/corpora/brown/ca19
EnglishAssistantCore/nltk_data/corpora/brown/ca20
EnglishAssistantCore/nltk_data/corpora/brown/ca21
EnglishAssistantCore/nltk_data/corpora/brown/ca22
EnglishAssistantCore/nltk_data/corpora/brown/ca23
EnglishAssistantCore/nltk_data/corpora/brown/ca24
EnglishAssistantCore/nltk_data/corpora/brown/ca25
EnglishAssistantCore/nltk_data/corpora/brown/ca26
EnglishAssistantCore/nltk_data/corpora/brown/ca27
EnglishAssistantCore/nltk_data/corpora/brown/ca28
EnglishAssistantCore/nltk_data/corpora/brown/ca29
EnglishAssistantCore/nltk_data/corpora/brown/ca30
EnglishAssistantCore/nltk_data/corpora/brown/ca31
EnglishAssistantCore/nltk_data/corpora/brown/ca32
EnglishAssistantCore/nltk_data/corpora/brown/ca33
EnglishAssistantCore/nltk_data/corpora/brown/ca34
EnglishAssistantCore/nltk_data/corpora/brown/ca35
EnglishAssistantCore/nltk_data/corpora/brown/ca36
englishassistantcore-1.0.6.dist-info/METADATA
englishassistantcore-1.0.6.dist-info/WHEEL
englishassistantcore-1.0.6.dist-info/licenses/LICENSE.txt
englishassistantcore-1.0.6.dist-info/RECORD
