Metadata-Version: 2.1
Name: EnglishAssistantCore
Version: 1.0.6
Summary: To help improve learning a language
Project-URL: Homepage, https://github.com/yasharsajadi/EnglishAssistantCore
Author-email: "Seyed Mousa Sajadi(WinCento)" <sajadimousa@gmail.com>
License-File: LICENSE.txt
Classifier: License :: OSI Approved :: MIT License
Classifier: Operating System :: OS Independent
Classifier: Programming Language :: Python :: 3
Requires-Python: >=3.10
Requires-Dist: googletrans==4.0.0rc1
Requires-Dist: nltk==3.8.1
Requires-Dist: pyttsx3==2.90
Requires-Dist: spacy==3.6.1
